gw2apiwrapper/__init__.py
gw2apiwrapper/accountapi.py
gw2apiwrapper/client.py
gw2apiwrapper/descriptions.py
gw2apiwrapper/functions.py
gw2apiwrapper/globalapi.py
gw2apiwrapper/tradingpost.py
gw2apiwrapper-2.7.5.dist-info/LICENSE
gw2apiwrapper-2.7.5.dist-info/METADATA
gw2apiwrapper-2.7.5.dist-info/WHEEL
gw2apiwrapper-2.7.5.dist-info/top_level.txt
gw2apiwrapper-2.7.5.dist-info/RECORD
