Metadata-Version: 2.1
Name: gw2apiwrapper
Version: 2.7.5
Summary: A simple wrapper around the offical Guild Wars 2 JSON API.
Home-page: https://github.com/PatchesPrime/gw2apiwrapper.git
Author: R. "Patches" S.
Author-email: patches@nullcorp.org
License: MIT
Keywords: guild wars gw2 arenanet api wrapper
Platform: UNKNOWN
Classifier: Development Status :: 4 - Beta
Classifier: Environment :: Console
Classifier: Intended Audience :: Developers
Classifier: License :: OSI Approved :: MIT License
Classifier: Operating System :: OS Independent
Classifier: Programming Language :: Python :: 3 :: Only
Classifier: Topic :: Games/Entertainment
Requires-Python: >=3.5
